main.py
ai_good_for_nothing-0.1.0.dist-info/METADATA
ai_good_for_nothing-0.1.0.dist-info/WHEEL
ai_good_for_nothing-0.1.0.dist-info/entry_points.txt
ai_good_for_nothing-0.1.0.dist-info/top_level.txt
ai_good_for_nothing-0.1.0.dist-info/RECORD
