Metadata-Version: 2.1
Name: ai-good-for-nothing
Version: 0.1.0
Summary: Add your description here
Requires-Python: >=3.8
Requires-Dist: requests >=2.32.3
